{
  "project_info": {
    "project_number": "177918479758",
    "project_id": "bulb-control-aecfc",
    "storage_bucket": "bulb-control-aecfc.appspot.com"
  },
  "client": [
    {
      "client_info": {
        "mobilesdk_app_id": "1:177918479758:android:efeba62c4f6f60e13de8df",
        "android_client_info": {
          "package_name": "com.example.led_control_2"
        }
      },
      "oauth_client": [],
      "api_key": [
        {
          "current_key": "AIzaSyCXwUqSNbOUd_O90BEZqdUHRgrJWTYgAYw"
        }
      ],
      "services": {
        "appinvite_service": {
          "other_platform_oauth_client": []
        }
      }
    }
  ],
  "configuration_version": "1"
}